#![allow(non_upper_case_globals)]
pub const aaload: u8 = 0x32;
pub const aastore: u8 = 0x53;
pub const aconst_null: u8 = 0x01;
pub const aload: u8 = 0x19;
pub const aload_0: u8 = 0x2A;
pub const aload_1: u8 = 0x2B;
pub const aload_2: u8 = 0x2C;
pub const aload_3: u8 = 0x2D;
pub const anewarray: u8 = 0xBD;
pub const areturn: u8 = 0xB0;
pub const arraylength: u8 = 0xBE;
pub const astore: u8 = 0x3A;
pub const astore_0: u8 = 0x4B;
pub const astore_1: u8 = 0x4C;
pub const astore_2: u8 = 0x4D;
pub const astore_3: u8 = 0x4E;
pub const athrow: u8 = 0xBF;
pub const baload: u8 = 0x33;
pub const bastore: u8 = 0x54;
pub const bipush: u8 = 0x10;
pub const caload: u8 = 0x34;
pub const castore: u8 = 0x55;
pub const checkcast: u8 = 0xC0;
pub const d2f: u8 = 0x90;
pub const d2i: u8 = 0x8E;
pub const d2l: u8 = 0x8F;
pub const dadd: u8 = 0x63;
pub const daload: u8 = 0x31;
pub const dastore: u8 = 0x52;
pub const dcmpg: u8 = 0x98;
pub const dcmpl: u8 = 0x97;
pub const dconst_0: u8 = 0x0E;
pub const dconst_1: u8 = 0x0F;
pub const ddiv: u8 = 0x6F;
pub const dload: u8 = 0x18;
pub const dload_0: u8 = 0x26;
pub const dload_1: u8 = 0x27;
pub const dload_2: u8 = 0x28;
pub const dload_3: u8 = 0x29;
pub const dmul: u8 = 0x6B;
pub const dneg: u8 = 0x77;
pub const drem: u8 = 0x73;
pub const dreturn: u8 = 0xAF;
pub const dstore: u8 = 0x39;
pub const dstore_0: u8 = 0x47;
pub const dstore_1: u8 = 0x48;
pub const dstore_2: u8 = 0x49;
pub const dstore_3: u8 = 0x4A;
pub const dsub: u8 = 0x67;
pub const dup: u8 = 0x59;
pub const dup_x1: u8 = 0x5A;
pub const dup_x2: u8 = 0x5B;
pub const dup2: u8 = 0x5C;
pub const dup2_x1: u8 = 0x5D;
pub const dup2_x2: u8 = 0x5E;
pub const f2d: u8 = 0x8D;
pub const f2i: u8 = 0x8B;
pub const f2l: u8 = 0x8C;
pub const fadd: u8 = 0x62;
pub const faload: u8 = 0x30;
pub const fastore: u8 = 0x51;
pub const fcmpg: u8 = 0x96;
pub const fcmpl: u8 = 0x95;
pub const fconst_0: u8 = 0x0B;
pub const fconst_1: u8 = 0x0C;
pub const fconst_2: u8 = 0x0D;
pub const fdiv: u8 = 0x6E;
pub const fload: u8 = 0x17;
pub const fload_0: u8 = 0x22;
pub const fload_1: u8 = 0x23;
pub const fload_2: u8 = 0x24;
pub const fload_3: u8 = 0x25;
pub const fmul: u8 = 0x6A;
pub const fneg: u8 = 0x76;
pub const frem: u8 = 0x72;
pub const freturn: u8 = 0xAE;
pub const fstore: u8 = 0x38;
pub const fstore_0: u8 = 0x43;
pub const fstore_1: u8 = 0x44;
pub const fstore_2: u8 = 0x45;
pub const fstore_3: u8 = 0x46;
pub const fsub: u8 = 0x66;
pub const getfield: u8 = 0xB4;
pub const getstatic: u8 = 0xB2;
pub const goto: u8 = 0xA7;
pub const goto_w: u8 = 0xC8;
pub const i2b: u8 = 0x91;
pub const i2c: u8 = 0x92;
pub const i2d: u8 = 0x87;
pub const i2f: u8 = 0x86;
pub const i2l: u8 = 0x85;
pub const i2s: u8 = 0x93;
pub const iadd: u8 = 0x60;
pub const iaload: u8 = 0x2E;
pub const iand: u8 = 0x7E;
pub const iastore: u8 = 0x4F;
pub const iconst_m1: u8 = 0x02;
pub const iconst_0: u8 = 0x03;
pub const iconst_1: u8 = 0x04;
pub const iconst_2: u8 = 0x05;
pub const iconst_3: u8 = 0x06;
pub const iconst_4: u8 = 0x07;
pub const iconst_5: u8 = 0x08;
pub const idiv: u8 = 0x6C;
pub const if_acmpeq: u8 = 0xA5;
pub const if_acmpne: u8 = 0xA6;
pub const if_icmpeq: u8 = 0x9F;
pub const if_icmpne: u8 = 0xA0;
pub const if_icmplt: u8 = 0xA1;
pub const if_icmpge: u8 = 0xA2;
pub const if_icmpgt: u8 = 0xA3;
pub const if_icmple: u8 = 0xA4;
pub const ifeq: u8 = 0x99;
pub const ifne: u8 = 0x9A;
pub const iflt: u8 = 0x9B;
pub const ifge: u8 = 0x9C;
pub const ifgt: u8 = 0x9D;
pub const ifle: u8 = 0x9E;
pub const ifnonnull: u8 = 0xC7;
pub const ifnull: u8 = 0xC6;
pub const iinc: u8 = 0x84;
pub const iload: u8 = 0x15;
pub const iload_0: u8 = 0x1A;
pub const iload_1: u8 = 0x1B;
pub const iload_2: u8 = 0x1C;
pub const iload_3: u8 = 0x1D;
pub const imul: u8 = 0x68;
pub const ineg: u8 = 0x74;
pub const instanceof: u8 = 0xC1;
pub const invokedynamic: u8 = 0xBA;
pub const invokeinterface: u8 = 0xB9;
pub const invokespecial: u8 = 0xB7;
pub const invokestatic: u8 = 0xB8;
pub const invokevirtual: u8 = 0xB6;
pub const ior: u8 = 0x80;
pub const irem: u8 = 0x70;
pub const ireturn: u8 = 0xAC;
pub const ishl: u8 = 0x78;
pub const ishr: u8 = 0x7A;
pub const istore: u8 = 0x36;
pub const istore_0: u8 = 0x3B;
pub const istore_1: u8 = 0x3C;
pub const istore_2: u8 = 0x3D;
pub const istore_3: u8 = 0x3E;
pub const isub: u8 = 0x64;
pub const iushr: u8 = 0x7C;
pub const ixor: u8 = 0x82;
pub const jsr: u8 = 0xA8;
pub const jsr_w: u8 = 0xC9;
pub const l2d: u8 = 0x8A;
pub const l2f: u8 = 0x89;
pub const l2i: u8 = 0x88;
pub const ladd: u8 = 0x61;
pub const laload: u8 = 0x2F;
pub const land: u8 = 0x7F;
pub const lastore: u8 = 0x50;
pub const lcmp: u8 = 0x94;
pub const lconst_0: u8 = 0x09;
pub const lconst_1: u8 = 0x0A;
pub const ldc: u8 = 0x12;
pub const ldc_w: u8 = 0x13;
pub const ldc2_w: u8 = 0x14;
pub const ldiv: u8 = 0x6D;
pub const lload: u8 = 0x16;
pub const lload_0: u8 = 0x1E;
pub const lload_1: u8 = 0x1F;
pub const lload_2: u8 = 0x20;
pub const lload_3: u8 = 0x21;
pub const lmul: u8 = 0x69;
pub const lneg: u8 = 0x75;
pub const lookupswitch: u8 = 0xAB;
pub const lor: u8 = 0x81;
pub const lrem: u8 = 0x71;
pub const lreturn: u8 = 0xAD;
pub const lshl: u8 = 0x79;
pub const lshr: u8 = 0x7B;
pub const lstore: u8 = 0x37;
pub const lstore_0: u8 = 0x3F;
pub const lstore_1: u8 = 0x40;
pub const lstore_2: u8 = 0x41;
pub const lstore_3: u8 = 0x42;
pub const lsub: u8 = 0x65;
pub const lushr: u8 = 0x7D;
pub const lxor: u8 = 0x83;
pub const monitorenter: u8 = 0xC2;
pub const monitorexit: u8 = 0xC3;
pub const multianewarray: u8 = 0xC5;
pub const new: u8 = 0xBB;
pub const newarray: u8 = 0xBC;
pub const nop: u8 = 0x00;
pub const pop: u8 = 0x57;
pub const pop2: u8 = 0x58;
pub const putfield: u8 = 0xB5;
pub const putstatic: u8 = 0xB3;
pub const ret: u8 = 0xA9;
pub const _return: u8 = 0xB1;
pub const saload: u8 = 0x35;
pub const sastore: u8 = 0x56;
pub const sipush: u8 = 0x11;
pub const swap: u8 = 0x5F;
pub const tableswitch: u8 = 0xAA;
pub const wide: u8 = 0xC4;
